rawdatafilter/__init__.cpython-39-x86_64-linux-gnu.so
rawdatafilter/filter.cpython-39-x86_64-linux-gnu.so
rawdatafilter/run_filter.cpython-39-x86_64-linux-gnu.so
rawdatafilter/run_filter.py
rawdatafilter-0.1.dist-info/entry_points.txt
rawdatafilter-0.1.dist-info/WHEEL
rawdatafilter-0.1.dist-info/METADATA
rawdatafilter-0.1.dist-info/RECORD
